sap_gui_engine/__init__.py
sap_gui_engine/exceptions.py
sap_gui_engine/managers/__init__.py
sap_gui_engine/managers/connection_manager.py
sap_gui_engine/managers/launcher.py
sap_gui_engine/managers/window_manager.py
sap_gui_engine/mappings/__init__.py
sap_gui_engine/mappings/login.py
sap_gui_engine/objects/__init__.py
sap_gui_engine/objects/gui_component.py
sap_gui_engine/objects/gui_table_control.py
sap_gui_engine/objects/sap_gui_element.py
sap_gui_engine/py.typed
sap_gui_engine/sap_gui_engine.py
sap_gui_engine/vkey.py
sap_gui_engine-0.1.3.dist-info/licenses/LICENSE
sap_gui_engine-0.1.3.dist-info/WHEEL
sap_gui_engine-0.1.3.dist-info/METADATA
sap_gui_engine-0.1.3.dist-info/RECORD
