Metadata-Version: 2.4
Name: sap-gui-engine
Version: 0.1.3
Summary: A framework for interacting with the SAP GUI Scripting API.
Author: fnxL
Author-email: fnxL <48607132+fnxL@users.noreply.github.com>
License-Expression: MIT
License-File: LICENSE
Requires-Dist: polars>=1.34.0
Requires-Dist: pywinauto>=0.6.9
Requires-Python: >=3.10
Project-URL: Homepage, https://github.com/fnxL/sap-gui-engine
Project-URL: Issues, https://github.com/fnxL/sap-gui-engine/issues
